jarvis/Colors.py
jarvis/Config.py
jarvis/Database.py
jarvis/Exiter.py
jarvis/Jarvis.py
jarvis/Logger.py
jarvis/MQTT.py
jarvis/Mime.py
jarvis/Security.py
jarvis/SetupTools.py
jarvis/ThreadPool.py
jarvis/__init__.py
open_jarvis-0.1.6.dist-info/DESCRIPTION.rst
open_jarvis-0.1.6.dist-info/METADATA
open_jarvis-0.1.6.dist-info/RECORD
open_jarvis-0.1.6.dist-info/WHEEL
open_jarvis-0.1.6.dist-info/metadata.json
open_jarvis-0.1.6.dist-info/top_level.txt
